stabilefrisur/.pypirc
stabilefrisur/__init__.py
stabilefrisur/save.py
stabilefrisur-0.1.0.dist-info/LICENSE
stabilefrisur-0.1.0.dist-info/WHEEL
stabilefrisur-0.1.0.dist-info/METADATA
stabilefrisur-0.1.0.dist-info/RECORD
