Metadata-Version: 2.3
Name: stabilefrisur
Version: 0.1.0
Summary: A short description of your package
Author-email: Your Name <your.email@example.com>
Requires-Python: >=3.10
Classifier: Programming Language :: Python :: 3
Classifier: License :: OSI Approved :: MIT License
Classifier: Operating System :: OS Independent
Requires-Dist: pandas
Requires-Dist: matplotlib
Project-URL: Homepage, https://github.com/stabilefrisur/stabilefrisur
